MANIFEST.in
README.md
setup.py
titan.conf
titan.db
monitors/README.md
plist/com.titan.dir.watcher.plist
plist/com.titan.runner.plist
plist/com.titan.watcher.plist
plist/com.titan.wifi.watcher.plist
scripts/titan
scripts/titan-watcher
titan/__init__.py
titan/cli.py
titan/config.py
titan/devicemgmt.py
titan/exceptions.py
titan/http.py
titan/launcher.py
titan/monitors.py
titan/report.py
titan/usage.py
titan/watcher.py
titan.egg-info/PKG-INFO
titan.egg-info/SOURCES.txt
titan.egg-info/dependency_links.txt
titan.egg-info/requires.txt
titan.egg-info/top_level.txt
titan/tools/__init__.py
titan/tools/__init__.pyc
titan/tools/data_science.py
titan/tools/decorators.py
titan/tools/filesystem.py
titan/tools/filesystem.pyc
titan/tools/network.py
titan/tools/network.pyc
titan/tools/nix.pyc
titan/tools/orm.py
titan/tools/orm.pyc
titan/tools/plist.py
titan/tools/plist.pyc
titan/tools/system.py
titan/tools/system.pyc
titan/tools/utilities.py
titan/tools/utilities.pyc