Metadata-Version: 1.1
Name: titan
Version: 1.3.2
Summary: titanOSX: OSX Secure Device Monitoring
Home-page: http://titanOSX.com
Author: Mike Mackintosh
Author-email: mike@shutterstock.com
License: MIT
Platform: UNKNOWN
Classifier: Intended Audience :: System Administrators
Classifier: License :: OSI Approved :: MIT License
Classifier: Operating System :: Unix
Classifier: Operating System :: POSIX
Classifier: Programming Language :: Python
Classifier: Programming Language :: Python :: 2.6
Classifier: Programming Language :: Python :: 2.7
Classifier: Programming Language :: Python :: 3.3
